transfer_controller/__init__.py
transfer_controller/utils/__init__.py
transfer_controller/utils/logging.py
transfer_controller-0.4.2.dist-info/METADATA
transfer_controller-0.4.2.dist-info/WHEEL
transfer_controller-0.4.2.dist-info/top_level.txt
transfer_controller-0.4.2.dist-info/RECORD
