Metadata-Version: 2.1
Name: transfer-controller
Version: 0.4.2
Summary: A module for controlling transfer sequences.
Author: Binho LLC
Author-email: support@binho.io
License: Private
Classifier: Development Status :: 3 - Alpha
Classifier: Intended Audience :: Developers
Classifier: Programming Language :: Python
Classifier: Programming Language :: Python :: 3
Classifier: Programming Language :: Python :: 3.8
Classifier: Programming Language :: Python :: 3.9
Requires-Python: >=3.9
